CONTRIBUTING.md
LICENSE
MANIFEST.in
README.md
settings.ini
setup.py
VitalSigns/BCPSS.py
VitalSigns/HUD.py
VitalSigns/__init__.py
VitalSigns/_nbdev.py
VitalSigns/acsDownload.py
VitalSigns/bidbaltimore.py
VitalSigns/citistat_dirtyst_clogged.py
VitalSigns/cityfinance.py
VitalSigns/closecrawl.py
VitalSigns/create.py
VitalSigns/dhr.py
VitalSigns/enoch.py
VitalSigns/fares.py
VitalSigns/fdic.py
VitalSigns/infousa.py
VitalSigns/liquor.py
VitalSigns/mdprop.py
VitalSigns/part1_crime.py
VitalSigns/rbintel.py
VitalSigns/tidyaddr.py
VitalSigns/treebaltimore.py
VitalSigns/utils.py
vSigns.egg-info/PKG-INFO
vSigns.egg-info/SOURCES.txt
vSigns.egg-info/dependency_links.txt
vSigns.egg-info/not-zip-safe
vSigns.egg-info/requires.txt
vSigns.egg-info/top_level.txt